pyemdd/__init__.py
pyemdd/_utils.py
pyemdd/emdd.py
pyemdd-0.5.9.dist-info/LICENSE
pyemdd-0.5.9.dist-info/METADATA
pyemdd-0.5.9.dist-info/WHEEL
pyemdd-0.5.9.dist-info/RECORD
