Metadata-Version: 2.1
Name: pyemdd
Version: 0.5.9
Summary: An EMDD-Mitos API client package
Author: Dimitrios Michail
Requires-Python: >=3.8
Classifier: Programming Language :: Python :: 3
Classifier: Programming Language :: Python :: 3.8
Classifier: Programming Language :: Python :: 3.9
Classifier: Programming Language :: Python :: 3.10
Classifier: Programming Language :: Python :: 3.11
Classifier: Programming Language :: Python :: 3.12
Requires-Dist: pydash (>=7.0.6,<8.0.0)
Requires-Dist: redis (>=5.0.0,<6.0.0)
